{
    "username": "EdmilsonPSOL",
    "position": "teste",
    "color": "teste",
    "following": [],
    "followers": [
        "EdmilsonPSOL",
        "GuajajaraSonia",
        "NiltoTatto",
        "LulaOficial",
        "depjorgesolla",
        "DepValmir",
        "BetoFaroPT",
        "MottaTarcisio",
        "JFMargarida",
        "Haddad_Fernando",
        "coelho_rodrigo",
        "RafaelMottaRN",
        "RogerioCorreia_",
        "natbonavides",
        "chico_dangelo",
        "helderbarbalho",
        "vicentinhojr",
        "BiradoPindare",
        "marchezan_",
        "dep_padrejoao",
        "jeanwyllys_real",
        "DepBrunaFurlan",
        "EliasVazGyn",
        "erikakokay",
        "randolfeap",
        "EdvaldoNogueira",
        "mariellefranco",
        "heldersalomao",
        "Patrus_Ananias",
        "senadorhumberto",
        "dasilvabenedita",
        "VICENTINHOPT",
        "lindberghfarias",
        "esuplicy",
        "costa_rui",
        "Glauber_Braga",
        "BohnGass",
        "mariadorosario",
        "HenriqueFontana",
        "jader_barbalho",
        "padilhando",
        "fernandapsol",
        "venezianovital",
        "lidicedamata",
        "guimaraes13PT",
        "CamiloPSB",
        "marciojerry",
        "zeca_dirceu",
        "alessandromolon",
        "MarceloFreixo",
        "perpetua_acre",
        "lucianagenro",
        "Alice_Portugal",
        "marceloramosam",
        "cirogomes",
        "samiabomfim",
        "ManuelaDavila",
        "pauloteixeira13"
    ]
}