{
    "username": "RodrigoMaia",
    "position": "teste",
    "color": "teste",
    "following": [],
    "followers": [
        "RodrigoMaia",
        "DamaresAlves",
        "SenadoraSelma",
        "tarcisiogdf",
        "KatiaSastre",
        "RomeuZema",
        "Sen_Oriovisto",
        "tabataamaralsp",
        "leiladovolei",
        "wilsonwitzel",
        "lucasvgonzalez",
        "cabojunioamaral",
        "AlexisFonteyne",
        "GeneralGirao",
        "deputadocajado",
        "SorayaThronicke",
        "DepJuscelino",
        "davialcolumbre",
        "NiltoTatto",
        "LulaOficial",
        "newton1510",
        "depjorgesolla",
        "GenPeternelli",
        "marciolabre",
        "DepValmir",
        "tumaoficial",
        "MagnoMalta",
        "AndreJanonesAdv",
        "depjpassarinho",
        "BetoFaroPT",
        "MottaTarcisio",
        "AfonsoFlorence",
        "HeitorSchuch",
        "Biakicis",
        "GiovaniFeltes",
        "_sergiosouza",
        "orlandosilva",
        "DepSostenes",
        "coelho_rodrigo",
        "robertodelucena",
        "RafaelMottaRN",
        "TerezaCrisMS",
        "depstefano",
        "RogerioCorreia_",
        "silascamara_",
        "natbonavides",
        "Everaldo_20",
        "EdmilsonPSOL",
        "RenanFilho_",
        "geovaniadesa",
        "andrepdt12",
        "EduardoBraga_AM",
        "MargaretCoelho",
        "Vanderlan_VC",
        "MarcosRogerio",
        "SandroAlex5555",
        "JoseMedeirosMT",
        "chico_dangelo",
        "helderbarbalho",
        "vicentinhojr",
        "carlossampaio_",
        "SenadorRogerio",
        "BiradoPindare",
        "LucianoDucci",
        "tassojereissati",
        "TiagoMitraud",
        "depleomonteiro",
        "MarceloCastroPI",
        "DepLuizCarlos",
        "EduardoLeite_",
        "felipecarreras",
        "walteralvesrn",
        "GuilhermeMussi",
        "DepJulioCesarPI",
        "joicehasselmann",
        "Silvio_CFilho",
        "alielmachado",
        "marchezan_",
        "dep_padrejoao",
        "depjuliodelgado",
        "Alceu_Moreira",
        "ViniciusPoit",
        "HugoMottaPB",
        "DepBrunaFurlan",
        "elizianegama",
        "EduardoGomesTO",
        "CacaLeao",
        "ratinho_jr",
        "LucasRedecker",
        "f_trad",
        "WolneyQueirozM",
        "iracemaportela",
        "senadorpetecao",
        "erikakokay",
        "Baleia_Rossi",
        "wevertonrocha",
        "rogerchequer",
        "EdvaldoNogueira",
        "uczai",
        "IzalciLucas",
        "enioverri",
        "LuisTibeOficial",
        "dep_paulinho",
        "profdorinha",
        "pedroocl",
        "DepAfonsoHamm",
        "dasilvabenedita",
        "VICENTINHOPT",
        "BolsonaroSP",
        "geraldoalckmin",
        "alvarodias_",
        "DeputadaMariana",
        "tuliogadelha",
        "esuplicy",
        "ProfIsrael",
        "costa_rui",
        "MarcoBertaiolli",
        "ciro_nogueira",
        "Alan_Rick",
        "jdoriajr",
        "marceloaro",
        "BohnGass",
        "mariadorosario",
        "HenriqueFontana",
        "rodrigoagost",
        "confuciomoura",
        "padilhando",
        "rubenspereirajr",
        "depHugoLeal",
        "GustinhoRibeiro",
        "fernandapsol",
        "venezianovital",
        "RicardoIzar",
        "dep_acoutinho",
        "jeronimogoergen",
        "Teresa_Surita",
        "nelsinhotrad",
        "fbezerracoelho",
        "ArnaldoJardim",
        "jorginhomello",
        "lidicedamata",
        "OsmarTerra",
        "DeputadoBacelar",
        "fatimabezerra",
        "RicardoBarrosPP",
        "ReginaldoLopes",
        "vanessa_grazz",
        "acmneto_",
        "guimaraes13PT",
        "CamiloPSB",
        "marciojerry",
        "Collor",
        "Altineu",
        "caleromarcelo",
        "zeca_dirceu",
        "MarceloFreixo",
        "CarlosZarattini",
        "perpetua_acre",
        "DanielCoelho23",
        "lucianagenro",
        "23rubensbueno",
        "pedropaulo",
        "mario_heringer",
        "Francischini_",
        "Domingos_Neto",
        "Alice_Portugal",
        "marceloramosam",
        "xicograziano",
        "pauloabiackel",
        "FlavioBolsonaro",
        "MichelTemer",
        "deputadopeninha",
        "PompeodeMattos",
        "paulopaim",
        "RodrigoCunhaAL",
        "PauloMartins10",
        "eduardodafonte",
        "LucianoRezende",
        "joseserra_",
        "vanderleimacris",
        "cirogomes",
        "darioberger",
        "ronaldocaiado",
        "gleisi",
        "KatiaAbreu",
        "maragabrilli",
        "samuelmoreira",
        "samiabomfim",
        "pauloteixeira13",
        "pauloganime",
        "dep_clarissa",
        "pedrowestphalen"
    ]
}