{
    "username": "rogerchequer",
    "position": "teste",
    "color": "teste",
    "following": [],
    "followers": [
        "rogerchequer",
        "Sen_Oriovisto",
        "lucasvgonzalez",
        "AlexisFonteyne",
        "lpbragancabr",
        "DepSostenes",
        "coelho_rodrigo",
        "TiagoMitraud",
        "marchezan_",
        "ViniciusPoit",
        "FernandoHoliday",
        "alvarodias_",
        "rodrigoagost",
        "caleromarcelo",
        "DanielCoelho23",
        "Francischini_",
        "xicograziano",
        "levyfidelix",
        "RodrigoMaia",
        "ronaldocaiado",
        "samuelmoreira",
        "pauloganime"
    ]
}