{
    "username": "zeca_dirceu",
    "position": "teste",
    "color": "teste",
    "following": [],
    "followers": [
        "zeca_dirceu",
        "ContaratoSenado",
        "Sen_Oriovisto",
        "nelsonhbarbosa",
        "NiltoTatto",
        "LulaOficial",
        "depjorgesolla",
        "DepValmir",
        "AndreJanonesAdv",
        "BetoFaroPT",
        "MottaTarcisio",
        "JFMargarida",
        "AfonsoFlorence",
        "Haddad_Fernando",
        "robertodelucena",
        "RafaelMottaRN",
        "RogerioCorreia_",
        "natbonavides",
        "EdmilsonPSOL",
        "nelsonpelegrino",
        "josiasgomesba",
        "SenadorRogerio",
        "wdiaspi",
        "BiradoPindare",
        "paulaodopt",
        "depleomonteiro",
        "GuilhermeMussi",
        "marchezan_",
        "dep_padrejoao",
        "DepBrunaFurlan",
        "EduardoGomesTO",
        "assis_carvalho",
        "DomingosSavioMG",
        "erikakokay",
        "randolfeap",
        "uczai",
        "enioverri",
        "heldersalomao",
        "Patrus_Ananias",
        "senadorhumberto",
        "dasilvabenedita",
        "VICENTINHOPT",
        "Daniel_PCdoB",
        "tuliogadelha",
        "lindberghfarias",
        "esuplicy",
        "costa_rui",
        "JoseAirtonPT",
        "BohnGass",
        "mariadorosario",
        "HenriqueFontana",
        "padilhando",
        "rubenspereirajr",
        "venezianovital",
        "dep_acoutinho",
        "jeronimogoergen",
        "vanderloubet",
        "RubensOtoni",
        "neyleprevost",
        "lidicedamata",
        "OsmarTerra",
        "deppauloguedes",
        "ReginaldoLopes",
        "vanessa_grazz",
        "guimaraes13PT",
        "CamiloPSB",
        "MarceloFreixo",
        "CarlosZarattini",
        "23rubensbueno",
        "Francischini_",
        "Alice_Portugal",
        "marceloramosam",
        "deputadopeninha",
        "paulopaim",
        "rfalcao13",
        "gleisi",
        "pauloteixeira13",
        "renildo"
    ]
}